LICENSE
README.md
jotform.py
setup.py
jotform.egg-info/PKG-INFO
jotform.egg-info/SOURCES.txt
jotform.egg-info/dependency_links.txt
jotform.egg-info/top_level.txt