Metadata-Version: 2.1
Name: jotform
Version: 1.2
Summary: JotForm API - Python Client
Home-page: http://api.jotform.com/docs/
Author: JotForm
Author-email: api@jotform.com
License-File: LICENSE
